llama_index/storage/docstore/tablestore/__init__.py
llama_index/storage/docstore/tablestore/base.py
llama_index_storage_docstore_tablestore-0.2.1.dist-info/METADATA
llama_index_storage_docstore_tablestore-0.2.1.dist-info/WHEEL
llama_index_storage_docstore_tablestore-0.2.1.dist-info/licenses/LICENSE
llama_index_storage_docstore_tablestore-0.2.1.dist-info/RECORD
