Metadata-Version: 2.4
Name: llama-index-storage-docstore-tablestore
Version: 0.2.1
Summary: llama-index docstore tablestore integration
Author-email: "xunjian.sl" <xunjian.sl@alibaba-inc.com>
License-Expression: MIT
License-File: LICENSE
Requires-Python: <4.0,>=3.9
Requires-Dist: llama-index-core<0.15,>=0.13.0
Requires-Dist: llama-index-storage-kvstore-tablestore<0.3,>=0.2.0
